nonebot_plugin_templates_draw/__init__.py
nonebot_plugin_templates_draw/api_handler.py
nonebot_plugin_templates_draw/config.py
nonebot_plugin_templates_draw/resources/FZMINGSTJW.TTF
nonebot_plugin_templates_draw/resources/fangsong_GB2312.ttf
nonebot_plugin_templates_draw/utils.py
nonebot_plugin_templates_draw-1.5.5.dist-info/METADATA
nonebot_plugin_templates_draw-1.5.5.dist-info/WHEEL
nonebot_plugin_templates_draw-1.5.5.dist-info/licenses/LICENSE
nonebot_plugin_templates_draw-1.5.5.dist-info/RECORD
