Metadata-Version: 2.4
Name: nonebot-plugin-templates-draw
Version: 1.5.5
Summary: NoneBot2 一个模板绘图插件
License-File: LICENSE
Keywords: nonebot2,nonebot-plugin-templates-draw
Author: padoru233
Requires-Python: >=3.9
Classifier: Programming Language :: Python :: 3
Classifier: Programming Language :: Python :: 3.9
Classifier: Programming Language :: Python :: 3.10
Classifier: Programming Language :: Python :: 3.11
Classifier: Programming Language :: Python :: 3.12
Classifier: Programming Language :: Python :: 3.13
Classifier: Programming Language :: Python :: 3.14
Requires-Dist: Pillow (>=8.4.0)
Requires-Dist: httpx (>=0.27.2,<1.0.0)
Requires-Dist: nonebot-adapter-onebot (>=2.0.0,<3.0.0)
Requires-Dist: nonebot-plugin-alconna (>=0.56.0)
Requires-Dist: nonebot-plugin-localstore (>=0.7.1,<0.8.0)
Requires-Dist: nonebot2 (>=2.2.0)
Requires-Dist: reportlab (>=4.2.0)
Project-URL: Homepage, https://github.com/padoru233/nonebot-plugin-templates-draw
Project-URL: Repository, https://github.com/padoru233/nonebot-plugin-templates-draw
